sondera/__init__.py
sondera/__main__.py
sondera/cli.py
sondera/exceptions.py
sondera/py.typed
sondera/settings.py
sondera/types.py
sondera/adk/__init__.py
sondera/adk/analyze.py
sondera/adk/plugin.py
sondera/harness/__init__.py
sondera/harness/abc.py
sondera/harness/cedar/__init__.py
sondera/harness/cedar/harness.py
sondera/harness/cedar/schema.py
sondera/harness/sondera/__init__.py
sondera/harness/sondera/_grpc.py
sondera/harness/sondera/harness.py
sondera/langgraph/__init__.py
sondera/langgraph/analyze.py
sondera/langgraph/exceptions.py
sondera/langgraph/graph.py
sondera/langgraph/middleware.py
sondera/proto/google/protobuf/any_pb2.py
sondera/proto/google/protobuf/any_pb2.pyi
sondera/proto/google/protobuf/any_pb2_grpc.py
sondera/proto/google/protobuf/duration_pb2.py
sondera/proto/google/protobuf/duration_pb2.pyi
sondera/proto/google/protobuf/duration_pb2_grpc.py
sondera/proto/google/protobuf/empty_pb2.py
sondera/proto/google/protobuf/empty_pb2.pyi
sondera/proto/google/protobuf/empty_pb2_grpc.py
sondera/proto/google/protobuf/struct_pb2.py
sondera/proto/google/protobuf/struct_pb2.pyi
sondera/proto/google/protobuf/struct_pb2_grpc.py
sondera/proto/google/protobuf/timestamp_pb2.py
sondera/proto/google/protobuf/timestamp_pb2.pyi
sondera/proto/google/protobuf/timestamp_pb2_grpc.py
sondera/proto/google/protobuf/wrappers_pb2.py
sondera/proto/google/protobuf/wrappers_pb2.pyi
sondera/proto/google/protobuf/wrappers_pb2_grpc.py
sondera/proto/sondera/__init__.py
sondera/proto/sondera/core/__init__.py
sondera/proto/sondera/core/v1/__init__.py
sondera/proto/sondera/core/v1/primitives_pb2.py
sondera/proto/sondera/core/v1/primitives_pb2.pyi
sondera/proto/sondera/core/v1/primitives_pb2_grpc.py
sondera/proto/sondera/harness/__init__.py
sondera/proto/sondera/harness/v1/__init__.py
sondera/proto/sondera/harness/v1/harness_pb2.py
sondera/proto/sondera/harness/v1/harness_pb2.pyi
sondera/proto/sondera/harness/v1/harness_pb2_grpc.py
sondera/strands/__init__.py
sondera/strands/analyze.py
sondera_harness-0.7.0.dist-info/licenses/LICENSE
sondera_harness-0.7.0.dist-info/METADATA
sondera_harness-0.7.0.dist-info/WHEEL
sondera_harness-0.7.0.dist-info/entry_points.txt
sondera_harness-0.7.0.dist-info/top_level.txt
sondera_harness-0.7.0.dist-info/RECORD
