Metadata-Version: 2.4
Name: sondera-harness
Version: 0.7.0
Summary: Sondera Harness SDK for Python - Agent governance and policy enforcement
Author-email: Sondera AI <sdk@sondera.ai>
License-Expression: MIT
Project-URL: Homepage, https://github.com/sondera-ai/harness-sdk-python
Project-URL: Documentation, https://docs.sondera.ai
Project-URL: Repository, https://github.com/sondera-ai/harness-sdk-python
Project-URL: Issues, https://github.com/sondera-ai/harness-sdk-python/issues
Project-URL: Changelog, https://github.com/sondera-ai/harness-sdk-python/blob/main/CHANGELOG.md
Keywords: ai,agents,governance,policy,guardrails,llm,langchain,langgraph
Classifier: Development Status :: 4 - Beta
Classifier: Intended Audience :: Developers
Classifier: Operating System :: OS Independent
Classifier: Programming Language :: Python :: 3
Classifier: Programming Language :: Python :: 3.12
Classifier: Programming Language :: Python :: 3.13
Classifier: Programming Language :: Python :: 3.14
Classifier: Topic :: Scientific/Engineering :: Artificial Intelligence
Classifier: Topic :: Security
Classifier: Typing :: Typed
Requires-Python: <3.15,>=3.12
License-File: LICENSE
Requires-Dist: cedar-python>=0.1.1
Requires-Dist: click>=8.0.0
Requires-Dist: click-default-group>=1.2.4
Requires-Dist: grpcio>=1.76.0
Requires-Dist: grpcio-tools>=1.76.0
Requires-Dist: httpx>=0.27.0
Requires-Dist: pydantic>=2.12.0
Requires-Dist: pydantic-settings>=2.12.0
Requires-Dist: textual>=6.11.0
Provides-Extra: adk
Requires-Dist: google-adk>=1.22.0; extra == "adk"
Provides-Extra: langgraph
Requires-Dist: langchain>=1.2.0; extra == "langgraph"
Requires-Dist: langgraph>=1.0.5; extra == "langgraph"
Provides-Extra: strands
Requires-Dist: strands-agents>=1.21.0; extra == "strands"
Provides-Extra: all
Requires-Dist: google-adk>=1.22.0; extra == "all"
Requires-Dist: langchain>=1.2.0; extra == "all"
Requires-Dist: langgraph>=1.0.5; extra == "all"
Requires-Dist: strands-agents>=1.21.0; extra == "all"
Dynamic: license-file
